dsxindexer/__init__.py
dsxindexer/configer.py
dsxindexer/functioner.py
dsxindexer/parser.py
dsxindexer/tokenizer.py
dsxindexer/factors/base_factor.py
dsxindexer/factors/float_factor.py
dsxindexer/factors/function_factor.py
dsxindexer/factors/int_factor.py
dsxindexer/factors/lparen_factor.py
dsxindexer/factors/minus_factor.py
dsxindexer/factors/newline_factor.py
dsxindexer/factors/string_factor.py
dsxindexer/factors/variable_factor.py
dsxindexer/operators/andor_operator.py
dsxindexer/operators/assign_operator.py
dsxindexer/operators/base_operator.py
dsxindexer/operators/equal_operator.py
dsxindexer/operators/grealess_operator.py
dsxindexer/operators/greaterthen_operator.py
dsxindexer/operators/minus_operator.py
dsxindexer/operators/muldiv_operator.py
dsxindexer/operators/plusminus_operator.py
dsxindexer/processors/base_processor.py
dsxindexer/processors/factor_processor.py
dsxindexer/processors/operator_processor.py
dsxindexer/processors/sindexer_processor.py
dsxindexer/sindexer/BOLL.py
dsxindexer/sindexer/BRAR.py
dsxindexer/sindexer/CCI.py
dsxindexer/sindexer/CDP.py
dsxindexer/sindexer/CR.py
dsxindexer/sindexer/DMA.py
dsxindexer/sindexer/DMI.py
dsxindexer/sindexer/EMV.py
dsxindexer/sindexer/EXPMA.py
dsxindexer/sindexer/KDJ.py
dsxindexer/sindexer/MACD.py
dsxindexer/sindexer/MIKE.py
dsxindexer/sindexer/OBV.py
dsxindexer/sindexer/PSY.py
dsxindexer/sindexer/ROC.py
dsxindexer/sindexer/RSI.py
dsxindexer/sindexer/TRIX.py
dsxindexer/sindexer/VR.py
dsxindexer/sindexer/WR.py
dsxindexer/sindexer/WVAD.py
dsxindexer/sindexer/base_sindexer.py
dsxindexer/sindexer/fomulas.py
dsxindexer/sindexer/sindexer_factory.py
dsxindexer/sindexer/base/cons_funcs.py
dsxindexer/sindexer/base/index_funcs.py
dsxindexer/sindexer/base/large_funcs.py
dsxindexer/sindexer/base/logical_funcs.py
dsxindexer/sindexer/base/math_funcs.py
dsxindexer/sindexer/base/price_funcs.py
dsxindexer/sindexer/base/refer_funcs.py
dsxindexer/sindexer/models/kline_model.py
dsxindexer-1.1.0.dist-info/LICENSE
dsxindexer-1.1.0.dist-info/METADATA
dsxindexer-1.1.0.dist-info/WHEEL
dsxindexer-1.1.0.dist-info/top_level.txt
dsxindexer-1.1.0.dist-info/RECORD
