Metadata-Version: 2.1
Name: dsxindexer
Version: 1.1.0
Summary: dsxindexer 是一个指标生成器，支持常用指标，自定义扩展指标算法，公式编辑功能
Home-page: https://github.com/dsxkline/dsxindexer
Author: fangyunsm
Author-email: fangyunsm <934476300@qq.com>
License: MIT License
Project-URL: Homepage, https://github.com/dsxkline/dsxindexer
Project-URL: Bug Tracker, https://github.com/dsxkline/dsxindexer/issues
Keywords: 通达信指标,公式编辑器,量化指标
Classifier: Programming Language :: Python :: 3
Classifier: License :: OSI Approved :: MIT License
Classifier: Operating System :: OS Independent
Requires-Python: >=3.6,<4
License-File: LICENSE
Requires-Dist: dsxquant (>=2.1.0)
Requires-Dist: numba (==0.56.4)
Requires-Dist: progressbar33 (==2.4)
